kisa.py
kisaBobPkgs.py
test_bob8gook.py
testbob8gook.py
whois.py
whoisBobPkgs.py
whoisBobPkgs-1.0.0.10.dist-info/METADATA
whoisBobPkgs-1.0.0.10.dist-info/WHEEL
whoisBobPkgs-1.0.0.10.dist-info/top_level.txt
whoisBobPkgs-1.0.0.10.dist-info/RECORD
