Metadata-Version: 2.1
Name: whoisBobPkgs
Version: 1.0.0.10
Summary: bob8gook
Home-page: https://github.com/woounnan
Author: bob8gook
Author-email: hyeok.jang@lotte.net
License: MIT
Requires-Python: >=3
